Workbook

Sheet Sales
A1: Order ID | B1: Due Date | C1: Name | D1: Gender | E1: Country | F1: Units | G1: Country_Units | H1: Revenue | I1: Column1
A2: 10507 | B2: 2/13/2024 | C2: Janet Murphy | D2: Female | E2: FR | F2: 91 | G2: =_xlfn.CONCAT(E2,F2) -> FR91 | H2: 36400
A3: 10534 | B3: 2/23/2024 | C3: Janice Clark | D3: Female | E3: IT | F3: 84 | G3: =_xlfn.CONCAT(E3,F3) -> IT84 | H3: 33440
A4: 10537 | B4: 2/14/2024 | C4: Charlotte Walker | D4: Female | E4: FR | F4: 84 | G4: =_xlfn.CONCAT(E4,F4) -> FR84 | H4: 26752 | J4: Filter Function | N4: Filter Only Words whose G is capital
A5: 10538 | B5: 2/14/2024 | C5: Hemant Shinde | D5: Female | E5: FR | F5: 84 | G5: =_xlfn.CONCAT(E5,F5) -> FR84 | H5: 26752 | J5: name | K5: gender | L5: units | N5: upgRad | O5: {=_xlfn._xlws.FILTER(N5:N7, EXACT(N5:N7, "upGrad"))} -> upGrad | P5: {=_xlfn._xlws.FILTER(N5:N7, ISNUMBER(FIND("G", N5:N7)))} -> upGrad
A6: 10542 | B6: 2/14/2024 | C6: Doris Nguyen | D6: Female | E6: IT | F6: 84 | G6: =_xlfn.CONCAT(E6,F6) -> IT84 | H6: 33440 | J6: Thomas Clark | K6: Male | L6: {=_xlfn._xlws.FILTER(F2:F31,(C2:C31=J6)*(D2:D31=K6))} -> 75 | N6: upGrad | O6: FILTER(N5:N7, EXACT(N5:N7, "upGrad"))
A7: 105406 | B7: 45415 | C7: Keith Roberts | D7: Male | E7: UK | F7: 84 | G7: =_xlfn.CONCAT(E7,F7) -> UK84 | H7: 20900 | L7: 87 | N7: Upgrad | O7: FILTER(N5:N7, ISNUMBER(FIND("G", N5:N7)))
A8: 10485 | B8: 45415 | C8: Kelly Jones | D8: Female | E8: JP | F8: 82 | G8: =_xlfn.CONCAT(E8,F8) -> JP82 | H8: 26240 | J8: FILTER(F2:F31,(C2:C31=J6)*(D2:D31=K6))
A9: 10453 | B9: 45415 | C9: Kennedi Singh | D9: Male | E9: ES | F9: 80 | G9: =_xlfn.CONCAT(E9,F9) -> ES80 | H9: 20000
A10: 10477 | B10: 45415 | C10: Joseph Mitchell | D10: Male | E10: FR | F10: 80 | G10: =_xlfn.CONCAT(E10,F10) -> FR80 | H10: 12000
A11: 10486 | B11: 45357 | C11: Steven Simpson | D11: Male | E11: US | F11: 80 | G11: =_xlfn.CONCAT(E11,F11) -> US80 | H11: 12000
A12: 10490 | B12: 2/14/2024 | C12: Kenneth Anderson | D12: Male | E12: JP | F12: 80 | G12: =_xlfn.CONCAT(E12,F12) -> JP80 | H12: 12000 | J12: Using Index-Match | K12: Name | L12: Units | M12: Country_Units | N12: Revenue
A13: 10502 | B13: 5/14/2024 | C13: Nicholas Gerrard | D13: Male | E13: ES | F13: 80 | G13: =_xlfn.CONCAT(E13,F13) -> ES80 | H13: 25600 | K13: Kelly Jones | L13: =INDEX($F$2:$H$31,MATCH(K13,$C$2:$C$31,0),MATCH(L$12,$F$1:$H$1,0)) -> 82 | M13: =INDEX($F$2:$H$31,MATCH($K13,$C$2:$C$31,0),MATCH(M$12,$F$1:$H$1,0)) -> JP82 | N13: =INDEX($F$2:$H$31,MATCH($K13,$C$2:$C$31,0),MATCH(N$12,$F$1:$H$1,0)) -> 26240
A14: 10523 | B14: 45634 | C14: Judith Lopez | D14: Female | E14: JP | F14: 80 | G14: =_xlfn.CONCAT(E14,F14) -> JP80 | H14: 32000 | K14: Kennedi Singh | L14: =INDEX($F$2:$H$31,MATCH(K14,$C$2:$C$31,0),MATCH(L$12,$F$1:$H$1,0)) -> 80 | M14: =INDEX($F$2:$H$31,MATCH($K14,$C$2:$C$31,0),MATCH(M$12,$F$1:$H$1,0)) -> ES80 | N14: =INDEX($F$2:$H$31,MATCH($K14,$C$2:$C$31,0),MATCH(N$12,$F$1:$H$1,0)) -> 20000
A15: 10525 | B15: 45576 | C15: Hannah Garcia | D15: Female | E15: ES | F15: 80 | G15: =_xlfn.CONCAT(E15,F15) -> ES80 | H15: 25536 | K15: Thomas Clark | L15: =INDEX($F$2:$H$31,MATCH(K15,$C$2:$C$31,0),MATCH(L$12,$F$1:$H$1,0)) -> 75 | M15: =INDEX($F$2:$H$31,MATCH($K15,$C$2:$C$31,0),MATCH(M$12,$F$1:$H$1,0)) -> JP75 | N15: =INDEX($F$2:$H$31,MATCH($K15,$C$2:$C$31,0),MATCH(N$12,$F$1:$H$1,0)) -> 18750
A16: 10535 | B16: 45871 | C16: Marilyn Allen | D16: Female | E16: IT | F16: 80 | G16: =_xlfn.CONCAT(E16,F16) -> IT80 | H16: 31840 | K16: Thomas Clark | L16: =INDEX($F$2:$H$31,MATCH(K16,$C$2:$C$31,0),MATCH(L$12,$F$1:$H$1,0)) -> 75 | M16: =INDEX($F$2:$H$31,MATCH($K16,$C$2:$C$31,0),MATCH(M$12,$F$1:$H$1,0)) -> JP75 | N16: =INDEX($F$2:$H$31,MATCH($K16,$C$2:$C$31,0),MATCH(N$12,$F$1:$H$1,0)) -> 18750
A17: 10461 | B17: 45905 | C17: Brendan Walls | D17: Male | E17: JP | F17: 76 | G17: =_xlfn.CONCAT(E17,F17) -> JP76 | H17: 30400
A18: 10506 | B18: 45846 | C18: Carolyn Muir | D18: Female | E18: FR | F18: 76 | G18: =_xlfn.CONCAT(E18,F18) -> FR76 | H18: 11400 | J18: Using Xlookup | K18: Name | L18: Units | M18: Country_Units | N18: Revenue
A19: 10531 | B19: 2/27/2024 | C19: Teresa Jarris | D19: Female | E19: IT | F19: 76 | G19: =_xlfn.CONCAT(E19,F19) -> IT76 | H19: 30400 | K19: =K13 -> Kelly Jones | L19: {=_xlfn.XLOOKUP($K19,$C$2:$C$31,$F$2:$H$31,"not found",0,1)} -> 82 | M19: JP82 | N19: 26240
A20: 10536 | B20: 2/22/2024 | C20: Beverly Young | D20: Female | E20: FR | F20: 76 | G20: =_xlfn.CONCAT(E20,F20) -> FR76 | H20: 11400 | K20: =K14 -> Kennedi Singh | L20: {=_xlfn.XLOOKUP($K20,$C$2:$C$31,$F$2:$H$31,"not found",0,1)} -> 80 | M20: ES80 | N20: 20000
A21: 10541 | B21: 45420 | C21: Brittany Hill | D21: Female | E21: IT | F21: 76 | G21: =_xlfn.CONCAT(E21,F21) -> IT76 | H21: 24320 | K21: =K15 -> Thomas Clark | L21: {=_xlfn.XLOOKUP($K21,$C$2:$C$31,$F$2:$H$31,"not found",0,1)} -> 75 | M21: JP75 | N21: 18750
A22: 10546 | B22: 6/16/2024 | C22: Christian Carter | D22: Male | E22: JP | F22: 76 | G22: =_xlfn.CONCAT(E22,F22) -> JP76 | H22: 24320 | K22: =K16 -> Thomas Clark | L22: {=_xlfn.XLOOKUP($K22,$C$2:$C$31,$F$2:$H$31,"not found",0,1)} -> 75 | M22: JP75 | N22: 18750
A23: 10501 | B23: 7/26/2024 | C23: Gary Sinclair | D23: Male | E23: ES | F23: 76 | G23: =_xlfn.CONCAT(E23,F23) -> ES76 | H23: 24320 | K23: Jaylynn Knapp | L23: {=_xlfn.XLOOKUP($K23,$C$2:$C$31,$F$2:$H$31,"not found",0,1)} -> 75 | M23: FR75 | N23: 11250
A24: 10456 | B24: 45449 | C24: Ivan Hines | D24: Male | E24: US | F24: 75 | G24: =_xlfn.CONCAT(E24,F24) -> US75 | H24: 24000
A25: 10457 | B25: 4/17/2024 | C25: Jonah Higgins | D25: Male | E25: US | F25: 75 | G25: =_xlfn.CONCAT(E25,F25) -> US75 | H25: 30000
A26: 10463 | B26: 2/27/2024 | C26: Lucia Mckay | D26: Female | E26: JP | F26: 75 | G26: =_xlfn.CONCAT(E26,F26) -> JP75 | H26: 11250 | J26: Using Dget | K26: Name | L26: Units | M26: Country_Units | N26: Revenue
A27: 10468 | B27: 2/22/2024 | C27: Jaylynn Knapp | D27: Female | E27: FR | F27: 75 | G27: =_xlfn.CONCAT(E27,F27) -> FR75 | H27: 11250 | K27: Kelly Jones | L27: =DGET($K$18:$N$23,L$26,K26:K27) -> 82 | M27: =DGET($K$18:$N$23,M$26,L26:L27) -> JP82 | N27: =DGET($K$18:$N$23,N$26,M26:M27) -> 26240
A28: 10470 | B28: 2/17/2024 | C28: Bryce Carpenter | D28: Male | E28: FR | F28: 75 | G28: =_xlfn.CONCAT(E28,F28) -> FR75 | H28: 18750
A29: 10473 | B29: 2/14/2024 | C29: Michael Filson | D29: Male | E29: US | F29: 75 | G29: =_xlfn.CONCAT(E29,F29) -> US75 | H29: 18750
A30: 10478 | B30: 2/17/2024 | C30: Thomas Clark | D30: Male | E30: JP | F30: 75 | G30: =_xlfn.CONCAT(E30,F30) -> JP75 | H30: 18750
A31: 10478 | B31: 45342 | C31: Thomas Clark | D31: Male | E31: JP | F31: 87 | G31: =_xlfn.CONCAT(E31,F31) -> JP87 | H31: 18750
C32: Thomas Clark | D32: Male | F32: 99 | J32: {=INDEX(_xlfn._xlws.FILTER(F2:F31,(C2:C31="Thomas Clark"),(D2:D31="Male")),1)} -> 75

Sheet Sheet1
A1: Order ID | B1: Due Date | C1: Name | D1: Gender | E1: Country | F1: Units | G1: Revenue
A2: 10507 | B2: 45335 | C2: Janet Murphy | D2: Female | E2: FR | F2: 91 | G2: 36400
A3: 10534 | B3: 45345 | C3: Janice Clark | D3: Female | E3: IT | F3: 84 | G3: 33440
A4: 10537 | B4: 45336 | C4: Charlotte Walker | D4: Female | E4: FR | F4: 84 | G4: 26752
A5: 10538 | B5: 45336 | C5: Hemant Shinde | D5: Female | E5: FR | F5: 84 | G5: 26752 | J5: Name | K5: Units | L5: Country | M5: Revenue
A6: 10542 | B6: 45336 | C6: Doris Nguyen | D6: Female | E6: IT | F6: 84 | G6: 33440 | J6: Janice Clark | K6: =DGET($A$1:$G$27,K$5,J5:J6) -> 84 | L6: =DGET($A$1:$G$27,L$5,K5:K6) -> #NUM! | M6: =DGET($A$1:$G$27,M$5,L5:L6) -> #VALUE!
A7: 10406 | B7: 45415 | C7: Keith Roberts | D7: Male | E7: UK | F7: 84 | G7: 20900 | J7: Hemant Shinde
A8: 10485 | B8: 45415 | C8: Kelly Jones | D8: Female | E8: JP | F8: 82 | G8: 26240
A9: 10453 | B9: 45415 | C9: Kennedi Singh | D9: Male | E9: ES | F9: 80 | G9: 20000
A10: 10477 | B10: 45415 | C10: Joseph Mitchell | D10: Male | E10: FR | F10: 80 | G10: 12000
A11: 10486 | B11: 45357 | C11: Steven Simpson | D11: Male | E11: US | F11: 80 | G11: 12000
A12: 10490 | B12: 45336 | C12: Kenneth Anderson | D12: Male | E12: JP | F12: 80 | G12: 12000
A13: 10502 | B13: 45426 | C13: Nicholas Gerrard | D13: Male | E13: ES | F13: 80 | G13: 25600
A14: 10523 | B14: 45634 | C14: Judith Lopez | D14: Female | E14: JP | F14: 80 | G14: 32000
A15: 10525 | B15: 45576 | C15: Hannah Garcia | D15: Female | E15: ES | F15: 80 | G15: 25536
A16: 10535 | B16: 45871 | C16: Marilyn Allen | D16: Female | E16: IT | F16: 80 | G16: 31840
A17: 10461 | B17: 45905 | C17: Brendan Walls | D17: Male | E17: JP | F17: 76 | G17: 30400
A18: 10506 | B18: 45846 | C18: Carolyn Muir | D18: Female | E18: FR | F18: 76 | G18: 11400
A19: 10531 | B19: 45349 | C19: Teresa Jarris | D19: Female | E19: IT | F19: 76 | G19: 30400
... A26: 10463 | B26: 45349 | C26: Lucia Mckay | D26: Female | E26: JP | F26: 75 | G26: 11250
A27: 10468 | B27: 45324

Sheet Question
B1: Vlookup
A2: 1 | B2: Using Order ID 10507, find the Revenue. | C2: =VLOOKUP(10507,Sales!A2:H31,8,FALSE) -> 36400 | D2: =_xlfn.XLOOKUP(10507,Sales!A2:A31,Sales!H2:H31,"NA",0) -> 36400
A3: 2 | B3: Find the Name of the customer whose Order ID is 10486. | C3: =VLOOKUP(10486,Sales!A2:H31,3,FALSE) -> Steven Simpson
A4: 3 | B4: Using Order ID 10546, fetch the Country. | C4: =VLOOKUP(10546,Sales!A2:H31,5,FALSE) -> JP
A5: 4 | B5: Using Order ID 10523, return the Country_Units value.
A6: 5 | B6: find Units for Order ID 99999. | C6: =IFERROR(VLOOKUP(99999,Sales!A2:H31,6,FALSE),"Not Present") -> Not Present
C7: Order ID | D7: 10507 | E7: 10534 | F7: 10537
C8: Name | D8: Janet Murphy | E8: Janice Clark | F8: Charlotte Walker
C9: Gender | D9: Female | E9: Female | F9: Female
C10: Country | D10: FR | E10: IT | F10: FR
C11: Units | D11: 91 | E11: 84 | F11: 84
B12: Hlookup | C12: Revenue | D12: 36400 | E12: 33440 | F12: 26752
A13: 1 | B13: Using Order ID 10507, find the Revenue using HLOOKUP.
A14: 2 | B14: Find the Country for Order ID 10534.
A15: 3 | B15: Using HLOOKUP, fetch Units for Order ID 10537.
B16: Xlookup
A17: 1 | B17: Find the Order ID for Customer Name = "Janet Murphy"
A18: 2 | B18: Find Units for Order ID = 99999 If not found, show "Order Not Available"
A19: 3 | B19: Find the Revenue for Order ID = 10523
A20: 4 | B20: Order ID = 10478 appears twice.
B21: Find the Units from the latest entry | C21: =_xlfn.XLOOKUP(10478,Sales!A2:A31,Sales!F2:F31,"NA",0,-1) -> 87
B22: Index+Match
A23: 1 | B23: Find Revenue for Order ID = 10507 | C23: =INDEX(Sales!H2:H31,MATCH(10507,Sales!A2:A31,0)) -> 36400
A24: 2 | B24: Find Country for Order ID = 10486 | C24: =INDEX(Sales!E2:E31,MATCH(10486,Sales!A2:A31,0)) -> US
A25: 3 | B25: Find Units sold for Order ID = 10502 | C25: =INDEX(Sales!F2:F31,MATCH(10502,Sales!A2:A31,0)) -> 80
A26: 4 | B26: Find Units sold for Order ID = 10502 | C26: =INDEX(Sales!F2:F31,MATCH(10502,Sales!A2:A31,0)) -> 80
A27: 5 | B27: Find Gender for Order ID = 10457 | C27: =INDEX(Sales!D2:D31,MATCH(10457,Sales!A2:A31,0)) -> Male
A28: 6 | B28: Find Revenue where:
B29: Name = Thomas Clark | C29: =INDEX(Sales!H2:H31,MATCH("Thomas Clark",Sales!C2:C31,0),MATCH(DATE(2024,2,20),Sales!B2:B31,0)) -> #REF! | D29: {=_xlfn.XLOOKUP(1, (Sales!C2:C31="Thomas Clark") * (Sales!B2:B31=DATE(2024,2,20)), Sales!H2:H31)} -> 18750
B30: Due Date = 2/20/2024 | C30: {=INDEX(Sales!H2:H31, MATCH(1, (Sales!C2:C31="Thomas Clark")* (Sales!B2:B31=DATE(2024,2,20)), 0))} -> 18750 | H30: {=INDEX(Sales!H2:H31,MATCH(1,(Sales!C2:C31="Thomas Clark")*(Sales!B2:B31=DATE(2024,2,20)),0))} -> 18750
A31: 7 | B31: Find Units where: | E31: INDEX(Sales!H2:H31,
B32: Country = JP | C32: {=INDEX(Sales!F2:F31,MATCH(1,(Sales!E2:E31="JP")*(Sales!D2:D31="Female"),0))} -> 82 | E32: MATCH(1,
B33: Gender = Female | E33: (Sales!C2:C31="Thomas Clark")*
A34: 8 | B34: Find Units where: | C34: {=INDEX(Sales!F2:F31,MATCH(1,(Sales!E2:E31="FR")*(Sales!D2:D31="Female"),0))} -> 91 | E34: (Sales!B2:B31=DATE(2024,2,20)),
B35: Country = FR | E35: 0))
B36: Gender = Female
A37: 9 | B37: Find Revenue where: | C37: {=INDEX(Sales!H2:H31,MATCH(1, (Sales!E2:E31="JP")* (Sales!F2:F31=87), 0))} -> 18750
B38: Country = JP
B39: Units = 87

Sheet Index+Match
C2: INDEX returns a value from a table based on position (row & column number). | D2: Go to this row and give me the value.”
C3: MATCH finds the position (row number) of a value in a list. | D3: “Where is this value located?”
E4: ID | F4: Name | G4: Department | H4: Salary
C5: MATCH finds the row number, | E5: 101 | F5: Amit | G5: Sales | H5: 45000
C6: INDEX returns the value from that row. | E6: 102 | F6: Neha | G6: HR | H6: 38000
E7: 103 | F7: Rahul | G7: Finance | H7: 52000
C8: =INDEX(Array,MATCH(Lookup_value,Lookup_array,match_type))
E9: Find Salary of Neha | G9: Match | H9: 2 | I9: =MATCH("Neha",F5:F7,0) -> 2
C10: XLOOKUP is mainly used for single-criteria lookups, | G10: Index | H10: 38000 | I10: =INDEX(H5:H7,2) -> 38000
C11: while INDEX + MATCH is used for multi-criteria (multiple conditions) lookups. | G11: Index+Match | H11: 38000 | I11: =INDEX(H5:H7,MATCH("Amit",F5:F7,0)) -> 45000
E12: Emp_ID | F12: Name | G12: Dept | H12: Month | I12: Sales
C13: XLOOKUP = Easy & single condition | E13: 101 | F13: Amit | G13: Sales | H13: Jan | I13: 50000
C14: INDEX MATCH = Powerful & multiple conditions | E14: 101 | F14: Amit | G14: Sales | H14: Feb | I14: 60000
E15: 102 | F15: Neha | G15: HR | H15: Jan | I15: 40000
C16: Single condition → normal INDEX MATCH
C17: Two conditions → multiply conditions inside MATCH | E17: Find Sales of Amit for Feb | G17: Vlookup | H17: 50000 | I17: =VLOOKUP("Amit",F13:I15,4,) -> 50000
E18: two conditions are involved (Name + Month) | G18: Xlookup | H18: 50000 | I18: =_xlfn.XLOOKUP("Amit",F12:F15,I12:I15,"not found",-1) -> 50000
G19: Index+Match | H19: 60000 | I19: {=INDEX(I13:I15,MATCH("Amit",F13:F15,0)*MATCH("Feb",H13:H15,0))} -> 60000

Sheet Hlookup
B2: order id | I2: 1111
B3: Name | C3: {=TRANSPOSE(Sales!C2:C8)} -> Janet Murphy | D3: Janice Clark | E3: Charlotte Walker | F3: Hemant Shinde | G3: Doris Nguyen | H3: Keith Roberts | I3: Kelly Jones
B4: Gender | C4: {=TRANSPOSE(Sales!D2:D6)} -> Female | D4: Female | E4: Female | F4: Female | G4: Female | H4: Male | I4: Female
B5: Revenue | C5: {=TRANSPOSE(Sales!H2:H8)} -> 36400 | D5: 33440 | E5: 26752 | F5: 26752 | G5: 33440 | H5: 20900 | I5: 26240
M8: HLOOKUP searches across the first row and returns data from another row.
M9: =HLOOKUP(lookup_value, table_array, row_index_num, [range_lookup])
H12: HLOOKUP | I12: VLOOKUP
H13: Horizontal search | I13: Vertical search

Sheet Vloopup
B2: Name | C2: Revenue
B3: Janet Murphy | C3: =VLOOKUP(B3,Sales!$C$1:$H$31,6,FALSE) -> 36400
B4: Janice Clark | C4: =VLOOKUP(B4,Sales!$C$1:$H$31,6,FALSE) -> 33440
B5: Charlotte Walker | C5: =VLOOKUP(B5,Sales!$C$1:$H$31,6,FALSE) -> 26752 | G5: VLOOKUP searches vertically in the first column and returns data from another column.
B6: Natalie Robinson | C6: =VLOOKUP(B6,Sales!$C$1:$H$31,6,FALSE) -> #N/A | G6: =VLOOKUP(lookup_value, table_array, col_index_num, [range_lookup])
B7: Doris Nguyen | C7: =VLOOKUP(B7,Sales!$C$1:$H$31,6,FALSE) -> 33440
G8: lookup_value = Find this = The value you want to search for.
G9: table_array = in this table = The full data range where Excel will search.
G10: col_index_num = return from this column = The column number from which to return the result.
G11: (range_lookup)Match = using this match type = Tells Excel how to match the value | H11: Value | I11: Meaning
G12: 0 | H12: FALSE | I12: Exact match
G13: 1 | H13: TRUE | I13: Approximate match

Sheet Xlookup
B3: Name | C3: {=TRANSPOSE(Sales!C2:C7)} -> Janet Murphy | D3: Janice Clark | E3: Charlotte Walker | F3: Hemant Shinde | G3: Doris Nguyen | H3: Keith Roberts
B4: Revenue | C4: {=TRANSPOSE(Sales!H2:H7)} -> 36400 | D4: 33440 | E4: 26752 | F4: 26752 | G4: 33440 | H4: 20900
J6: Janice Clark
J7: Charlotte Walker
